django_rewind/__init__.py
django_rewind/admin.py
django_rewind/apps.py
django_rewind/executor.py
django_rewind/loader.py
django_rewind/models.py
django_rewind/recorder.py
django_rewind/management/__init__.py
django_rewind/management/commands/__init__.py
django_rewind/management/commands/backfill_migration_code.py
django_rewind/management/commands/show_stored_migrations.py
django_rewind/management/commands/verify_migrations.py
django_rewind/migrations/0001_initial.py
django_rewind/migrations/__init__.py
django_rewind/templates/admin/django_rewind/migrationcode/change_list.html
django_rewind-0.1.0.dist-info/METADATA
django_rewind-0.1.0.dist-info/WHEEL
django_rewind-0.1.0.dist-info/licenses/LICENSE
django_rewind-0.1.0.dist-info/RECORD
