Metadata-Version: 2.4
Name: django-rewind
Version: 0.1.0
Summary: Roll back Django migrations even when the migration file is deleted
Project-URL: Homepage, https://github.com/HartBrook/django-rewind
Project-URL: Documentation, https://github.com/HartBrook/django-rewind#readme
Project-URL: Repository, https://github.com/HartBrook/django-rewind
Project-URL: Issues, https://github.com/HartBrook/django-rewind/issues
Project-URL: Changelog, https://github.com/HartBrook/django-rewind/blob/main/CHANGELOG.md
Author-email: Cody Hart <mrcodyhart@gmail.com>
Maintainer-email: Cody Hart <mrcodyhart@gmail.com>
License: MIT
License-File: LICENSE
Keywords: database,django,django-migrations,migration-management,migrations,rollback
Classifier: Development Status :: 4 - Beta
Classifier: Environment :: Web Environment
Classifier: Framework :: Django
Classifier: Framework :: Django :: 3.2
Classifier: Framework :: Django :: 4.2
Classifier: Framework :: Django :: 5.0
Classifier: Framework :: Django :: 5.1
Classifier: Intended Audience :: Developers
Classifier: License :: OSI Approved :: MIT License
Classifier: Operating System :: OS Independent
Classifier: Programming Language :: Python
Classifier: Programming Language :: Python :: 3
Classifier: Programming Language :: Python :: 3.9
Classifier: Programming Language :: Python :: 3.10
Classifier: Programming Language :: Python :: 3.11
Classifier: Programming Language :: Python :: 3.12
Classifier: Topic :: Database
Classifier: Topic :: Internet :: WWW/HTTP :: Dynamic Content
Classifier: Topic :: Software Development :: Libraries :: Python Modules
Requires-Python: >=3.9
Requires-Dist: django<6.0,>=3.2
Provides-Extra: build
Requires-Dist: build<2.0,>=0.10.0; extra == 'build'
Requires-Dist: twine<7.0,>=4.0.0; extra == 'build'
Provides-Extra: dev
Requires-Dist: black<26.0,>=23.0.0; extra == 'dev'
Requires-Dist: build<2.0,>=0.10.0; extra == 'dev'
Requires-Dist: django-stubs<6.0,>=4.2.0; extra == 'dev'
Requires-Dist: flake8<8.0,>=6.0.0; extra == 'dev'
Requires-Dist: isort<6.0,>=5.12.0; extra == 'dev'
Requires-Dist: mypy<2.0,>=1.0.0; extra == 'dev'
Requires-Dist: pre-commit<4.0,>=3.0.0; extra == 'dev'
Requires-Dist: pytest-cov<8.0,>=4.0.0; extra == 'dev'
Requires-Dist: pytest-django<6.0,>=4.5.0; extra == 'dev'
Requires-Dist: pytest<10.0,>=7.0.0; extra == 'dev'
Requires-Dist: tox<5.0,>=4.0.0; extra == 'dev'
Requires-Dist: twine<7.0,>=4.0.0; extra == 'dev'
Provides-Extra: lint
Requires-Dist: black<26.0,>=23.0.0; extra == 'lint'
Requires-Dist: flake8<8.0,>=6.0.0; extra == 'lint'
Requires-Dist: isort<6.0,>=5.12.0; extra == 'lint'
Requires-Dist: pre-commit<4.0,>=3.0.0; extra == 'lint'
Provides-Extra: test
Requires-Dist: pytest-cov<8.0,>=4.0.0; extra == 'test'
Requires-Dist: pytest-django<6.0,>=4.5.0; extra == 'test'
Requires-Dist: pytest<10.0,>=7.0.0; extra == 'test'
Provides-Extra: tox
Requires-Dist: tox<5.0,>=4.0.0; extra == 'tox'
Provides-Extra: type
Requires-Dist: django-stubs<6.0,>=4.2.0; extra == 'type'
Requires-Dist: mypy<2.0,>=1.0.0; extra == 'type'
